lgtm_lint/__init__.py
lgtm_lint/__main__.py
lgtm_lint-1.0.3.dist-info/LICENSE
lgtm_lint-1.0.3.dist-info/METADATA
lgtm_lint-1.0.3.dist-info/WHEEL
lgtm_lint-1.0.3.dist-info/entry_points.txt
lgtm_lint-1.0.3.dist-info/top_level.txt
lgtm_lint-1.0.3.dist-info/RECORD
