Metadata-Version: 2.1
Name: lgtm-lint
Version: 1.0.3
Summary: A fully featured 'Looks good to me!' linter.
Author-email: Paul Maxwell <maxwellpaulm@gmail.com>, Zach Spar <zachspar@gmail.com>
Project-URL: Homepage, https://github.com/maxwellpaulm/lgtm-lint
Project-URL: Bug Tracker, https://github.com/maxwellpaulm/lgtm-lint/issues
Classifier: Development Status :: 5 - Production/Stable
Classifier: Intended Audience :: Developers
Classifier: Programming Language :: Python :: 3.7
Classifier: Programming Language :: Python :: 3.8
Classifier: Programming Language :: Python :: 3.9
Classifier: Programming Language :: Python :: 3.10
Classifier: Programming Language :: Python :: 3.11
Classifier: License :: OSI Approved :: The Unlicense (Unlicense)
Classifier: Operating System :: OS Independent
Requires-Python: >=3.7
License-File: LICENSE
